pinecone_read_only_mcp/__init__.py
pinecone_read_only_mcp/__main__.py
pinecone_read_only_mcp/pinecone_client.py
pinecone_read_only_mcp/server.py
pinecone_read_only_mcp-0.1.0.dist-info/METADATA
pinecone_read_only_mcp-0.1.0.dist-info/WHEEL
pinecone_read_only_mcp-0.1.0.dist-info/entry_points.txt
pinecone_read_only_mcp-0.1.0.dist-info/licenses/LICENSE
pinecone_read_only_mcp-0.1.0.dist-info/RECORD
