Metadata-Version: 2.4
Name: pinecone-read-only-mcp
Version: 0.1.0
Summary: A Model Context Protocol (MCP) server that provides semantic search over Pinecone vector databases using hybrid search (dense + sparse) with reranking.
Project-URL: Homepage, https://cppalliance.org/
Project-URL: Repository, https://github.com/iTinkerBell/pinecone-read-only-mcp.git
Project-URL: Issues, https://github.com/iTinkerBell/pinecone-read-only-mcp/issues
Project-URL: Documentation, https://github.com/iTinkerBell/pinecone-read-only-mcp/blob/main/README.md
Project-URL: Changelog, https://github.com/iTinkerBell/pinecone-read-only-mcp/blob/main/CHANGELOG.md
Project-URL: Source Code, https://github.com/iTinkerBell/pinecone-read-only-mcp
Author-email: Will Pak <will@cppalliance.org>
Maintainer-email: Will Pak <will@cppalliance.org>
License: BSL-1.0
License-File: LICENSE
Keywords: mcp,pinecone,rag,read-only,semantic-search
Classifier: Development Status :: 4 - Beta
Classifier: Intended Audience :: Developers
Classifier: License :: OSI Approved :: Boost Software License 1.0 (BSL-1.0)
Classifier: Programming Language :: Python :: 3
Classifier: Programming Language :: Python :: 3.10
Classifier: Programming Language :: Python :: 3.11
Classifier: Programming Language :: Python :: 3.12
Classifier: Programming Language :: Python :: 3.13
Classifier: Topic :: Scientific/Engineering :: Artificial Intelligence
Classifier: Topic :: Software Development :: Documentation
Requires-Python: >=3.10
Requires-Dist: anyio>=4.5.0
Requires-Dist: click>=8.1.8
Requires-Dist: mcp>=1.6.0
Requires-Dist: pinecone>=5.0.0
Requires-Dist: pydantic>=2.0.0
Requires-Dist: python-dotenv>=1.0.0
